nonebot_plugin_tavily/__init__.py
nonebot_plugin_tavily/client.py
nonebot_plugin_tavily/config.py
nonebot_plugin_tavily/commands/__init__.py
nonebot_plugin_tavily/commands/crawl.py
nonebot_plugin_tavily/commands/extract.py
nonebot_plugin_tavily/commands/search.py
nonebot_plugin_tavily-0.1.0.dist-info/METADATA
nonebot_plugin_tavily-0.1.0.dist-info/WHEEL
nonebot_plugin_tavily-0.1.0.dist-info/licenses/LICENSE
nonebot_plugin_tavily-0.1.0.dist-info/RECORD
