Metadata-Version: 2.4
Name: nonebot-plugin-tavily
Version: 0.1.0
Summary: Tavily Search API plugin for NoneBot2
Author-email: gsskk <your.email@example.com>
License: MIT License
License-File: LICENSE
Requires-Python: >=3.10
Requires-Dist: nonebot-plugin-alconna>=0.50.2
Requires-Dist: nonebot2>=2.3.0
Requires-Dist: tavily-python>=0.5.4
